hltv_fetch/__init__.py
hltv_fetch/functions.py
hltv_fetch-0.1.1.dist-info/LICENSE
hltv_fetch-0.1.1.dist-info/METADATA
hltv_fetch-0.1.1.dist-info/WHEEL
hltv_fetch-0.1.1.dist-info/top_level.txt
hltv_fetch-0.1.1.dist-info/RECORD
