Metadata-Version: 2.1
Name: hltv-fetch
Version: 0.1.1
Summary: My very own HLTV API
Author: Lilseec
Classifier: Programming Language :: Python :: 3
Classifier: License :: OSI Approved :: MIT License
Classifier: Operating System :: OS Independent
Requires-Python: >=3.6
License-File: LICENSE
Requires-Dist: beautifulsoup4
Requires-Dist: lxml
